fcast/__init__.py
fcast/fcast.py
fcast_client-0.3.dist-info/METADATA
fcast_client-0.3.dist-info/WHEEL
fcast_client-0.3.dist-info/top_level.txt
fcast_client-0.3.dist-info/RECORD
