Metadata-Version: 2.1
Name: fcast-client
Version: 0.3
Summary: A Python client wrapper for the video streaming receiver Fcast.
Home-page: https://github.com/developer90210brr/fcast-wrapper
Author: cassdev
Author-email: admin@cassdev.com
Classifier: Programming Language :: Python :: 3
Classifier: License :: OSI Approved :: MIT License
Classifier: Operating System :: OS Independent
